pymc_learn_sphinx_theme/__init__.py
pymc_learn_sphinx_theme/layout.html
pymc_learn_sphinx_theme/theme.conf
pymc_learn_sphinx_theme/static/css/explore.css
pymc_learn_sphinx_theme/static/css/nbsphinx.css
pymc_learn_sphinx_theme/static/css/style.css
pymc_learn_sphinx_theme/static/images/pymc-learn-logo-square.svg
pymc_learn_sphinx_theme/static/images/pymc-learn-logo.png
pymc_learn_sphinx_theme/static/images/pymc-learn-logo.svg
pymc_learn_sphinx_theme/static/images/pymc-learn.png
pymc_learn_sphinx_theme/static/images/pymc-learn.svg
pymc_learn_sphinx_theme/static/images/pymc3_logo.png
pymc_learn_sphinx_theme/static/images/pymc_learn_logo.png
pymc_learn_sphinx_theme/static/images/favicon/android-icon-144x144.png
pymc_learn_sphinx_theme/static/images/favicon/android-icon-192x192.png
pymc_learn_sphinx_theme/static/images/favicon/android-icon-36x36.png
pymc_learn_sphinx_theme/static/images/favicon/android-icon-48x48.png
pymc_learn_sphinx_theme/static/images/favicon/android-icon-72x72.png
pymc_learn_sphinx_theme/static/images/favicon/android-icon-96x96.png
pymc_learn_sphinx_theme/static/images/favicon/apple-icon-114x114.png
pymc_learn_sphinx_theme/static/images/favicon/apple-icon-120x120.png
pymc_learn_sphinx_theme/static/images/favicon/apple-icon-144x144.png
pymc_learn_sphinx_theme/static/images/favicon/apple-icon-152x152.png
pymc_learn_sphinx_theme/static/images/favicon/apple-icon-180x180.png
pymc_learn_sphinx_theme/static/images/favicon/apple-icon-57x57.png
pymc_learn_sphinx_theme/static/images/favicon/apple-icon-60x60.png
pymc_learn_sphinx_theme/static/images/favicon/apple-icon-72x72.png
pymc_learn_sphinx_theme/static/images/favicon/apple-icon-76x76.png
pymc_learn_sphinx_theme/static/images/favicon/apple-icon-precomposed.png
pymc_learn_sphinx_theme/static/images/favicon/apple-icon.png
pymc_learn_sphinx_theme/static/images/favicon/favicon-16x16.png
pymc_learn_sphinx_theme/static/images/favicon/favicon-32x32.png
pymc_learn_sphinx_theme-0.1.5.dist-info/LICENSE.txt
pymc_learn_sphinx_theme-0.1.5.dist-info/METADATA
pymc_learn_sphinx_theme-0.1.5.dist-info/WHEEL
pymc_learn_sphinx_theme-0.1.5.dist-info/entry_points.txt
pymc_learn_sphinx_theme-0.1.5.dist-info/top_level.txt
pymc_learn_sphinx_theme-0.1.5.dist-info/RECORD
