Metadata-Version: 2.1
Name: pymc-learn-sphinx-theme
Version: 0.1.5
Summary: Pymc-learn theme for Sphinx
Home-page: https://github.com/pymc-learn/pymc-learn-sphinx-theme/
Author: Pymc-learn Developers
Author-email: UNKNOWN
License: BSD
Platform: UNKNOWN
Requires-Dist: sphinx-rtd-theme
Requires-Dist: dask-sphinx-theme
